{
  "type": "EFFECT_REQUESTED",
  "recordedAt": "2026-03-26T11:56:43.859Z",
  "data": {
    "effectId": "01KMN021Y7MRG3HFA8YA6S8ERB",
    "invocationKey": "network-map-explorer:S000007:implementation-task",
    "invocationHash": "1919e2563acebace14a7b2eb4d39804ad10249906bc57285daf82722e47a46f1",
    "stepId": "S000007",
    "taskId": "implementation-task",
    "kind": "agent",
    "label": "Task 6: Mount Router and Write API Tests",
    "taskDefRef": "tasks/01KMN021Y7MRG3HFA8YA6S8ERB/task.json"
  },
  "checksum": "17cf4f59c253e19a0f221c246f6ad82dea8dc989eb00a734c7291618aaf11476"
}
