{
  "schemaVersion": "2026.01.results-v1",
  "effectId": "01KMN01PT6CQ3RQE66D3ATG9PY",
  "taskId": "implementation-task",
  "invocationKey": "network-map-explorer:S000006:implementation-task",
  "status": "ok",
  "result": {
    "status": "completed",
    "taskName": "API Router",
    "taskNumber": 5,
    "testsPassed": true
  },
  "startedAt": "2026-03-26T11:56:38.419Z",
  "finishedAt": "2026-03-26T11:56:38.419Z",
  "value": {
    "status": "completed",
    "taskName": "API Router",
    "taskNumber": 5,
    "testsPassed": true
  }
}
